latex_generator_itmo_aniciya/__init__.py
latex_generator_itmo_aniciya/core.py
latex_generator_itmo_aniciya/utils.py
latex_generator_itmo_aniciya-0.2.0.dist-info/LICENSE
latex_generator_itmo_aniciya-0.2.0.dist-info/METADATA
latex_generator_itmo_aniciya-0.2.0.dist-info/WHEEL
latex_generator_itmo_aniciya-0.2.0.dist-info/RECORD
