Metadata-Version: 2.1
Name: latex-generator-itmo-aniciya
Version: 0.2.0
Summary: Генератор LaTeX в функциональном стиле
Home-page: https://github.com/aniciya777/latex_generator_itmo_aniciya
License: MIT
Keywords: latex,generator,itmo
Author: aniciya777
Author-email: kisaost777@gmail.com
Requires-Python: >=3.9,<4.0
Classifier: License :: OSI Approved :: MIT License
Classifier: Programming Language :: Python :: 3
Classifier: Programming Language :: Python :: 3.9
Classifier: Programming Language :: Python :: 3.10
Classifier: Programming Language :: Python :: 3.11
Classifier: Programming Language :: Python :: 3.12
Project-URL: Documentation, https://github.com/aniciya777/latex_generator_iЦЦtmo_aniciya#readme
Project-URL: Repository, https://github.com/aniciya777/latex_generator_itmo_aniciya
